README.txt
setup.cfg
setup.py
docs/HISTORY.txt
docs/INSTALL.txt
docs/LICENSE.GPL
docs/LICENSE.txt
kss/__init__.py
kss.plugin.cns.egg-info/PKG-INFO
kss.plugin.cns.egg-info/SOURCES.txt
kss.plugin.cns.egg-info/dependency_links.txt
kss.plugin.cns.egg-info/entry_points.txt
kss.plugin.cns.egg-info/namespace_packages.txt
kss.plugin.cns.egg-info/not-zip-safe
kss.plugin.cns.egg-info/requires.txt
kss.plugin.cns.egg-info/top_level.txt
kss/plugin/__init__.py
kss/plugin/cns/__init__.py
kss/plugin/cns/configure.zcml
kss/plugin/cns/tests.py
kss/plugin/cns/commands/__init__.py
kss/plugin/cns/commands/commands.py
kss/plugin/cns/commands/configure.zcml
kss/plugin/cns/commands/interfaces.py
kss/plugin/cns/plugins/__init__.py
kss/plugin/cns/plugins/alerttext.js
kss/plugin/cns/plugins/autocomplete.css
kss/plugin/cns/plugins/autocomplete.js
kss/plugin/cns/plugins/autocomplete.py
kss/plugin/cns/plugins/calendar.js
kss/plugin/cns/plugins/configure.zcml
kss/plugin/cns/plugins/confirm.js
kss/plugin/cns/plugins/datepickercalendar.css
kss/plugin/cns/plugins/dynamicposition.js
kss/plugin/cns/plugins/openwindow.js
kss/plugin/cns/plugins/plugin.js
kss/plugin/cns/plugins/refreshpage.js
kss/plugin/cns/plugins/removeattribute.js
kss/plugin/cns/plugins/valuesetter.js
kss/plugin/cns/profiles/default/cssregistry.xml
kss/plugin/cns/profiles/default/metadata.xml
