Metadata-Version: 1.0
Name: kss.plugin.cns
Version: 1.1
Summary: Various KSS plugins
Home-page: http://svn.plone.org/svn/collective/kss.plugin.cns
Author: Matous Hora
Author-email: matous.hora@dms4u.cz
License: GPL
Keywords: kss
Platform: UNKNOWN
Classifier: Framework :: Plone
Classifier: Programming Language :: Python
Classifier: Topic :: Software Development :: Libraries :: Python Modules
